AOMUSE/__init__.py
AOMUSE/constants.py
AOMUSE/ao/__init__.py
AOMUSE/ao/muse_db.py
AOMUSE/db/Database.py
AOMUSE/db/__init__.py
AOMUSE/process/__init__.py
AOMUSE/process/process.py
AOMUSE/utils/__init__.py
AOMUSE/utils/preprocess.py
AOMUSE-0.0.10.dist-info/LICENSE
AOMUSE-0.0.10.dist-info/METADATA
AOMUSE-0.0.10.dist-info/WHEEL
AOMUSE-0.0.10.dist-info/top_level.txt
AOMUSE-0.0.10.dist-info/RECORD
