Metadata-Version: 2.1
Name: AOMUSE
Version: 0.0.10
Summary: AO Muse package
Home-page: https://github.com/AxlKings/AOMUSE
Author: AxelReyesO (Axel Reyes O)
Author-email: <axel.reyes@sansano.usm.cl>
License: MIT
Keywords: python adaptative optics muse
Platform: UNKNOWN
Classifier: Development Status :: 1 - Planning
Classifier: Intended Audience :: Developers
Classifier: Programming Language :: Python :: 3
Classifier: Operating System :: Unix
Classifier: Operating System :: MacOS :: MacOS X
Classifier: Operating System :: Microsoft :: Windows
License-File: LICENSE
Requires-Dist: numpy
Requires-Dist: pandas
Requires-Dist: pony
Requires-Dist: astropy
